simp_sql/__init__.py
simp_sql/db_connection.py
simp_sql/query_generator.py
simp_sql-0.1.6.dist-info/LICENSE
simp_sql-0.1.6.dist-info/METADATA
simp_sql-0.1.6.dist-info/WHEEL
simp_sql-0.1.6.dist-info/top_level.txt
simp_sql-0.1.6.dist-info/RECORD
