Metadata-Version: 2.1
Name: simp_sql
Version: 0.1.6
Summary: A package that generates and optimizes SQL queries.
Author: Nikhil Kumawat
Classifier: Programming Language :: Python :: 3
Classifier: License :: OSI Approved :: MIT License
Classifier: Operating System :: OS Independent
Requires-Python: >=3.6
License-File: LICENSE
Requires-Dist: mysql-connector-python>=8.0.0
